metro_db/__init__.py
metro_db/_queries.py
metro_db/_version.py
metro_db/metro_db.py
metro_db/peek.py
metro_db/sqlite_db.py
metro_db/types.py
metro_db-0.6.1.dist-info/METADATA
metro_db-0.6.1.dist-info/WHEEL
metro_db-0.6.1.dist-info/entry_points.txt
metro_db-0.6.1.dist-info/licenses/LICENSE
metro_db-0.6.1.dist-info/RECORD
