Metadata-Version: 2.4
Name: metro_db
Version: 0.6.1
Summary: A wrapper around the sqlite3 database for easy database development
Project-URL: Homepage, https://github.com/DLu/metro_db
Project-URL: Bug Tracker, https://github.com/DLu/metro_db/issues
Author-email: "David V. Lu!!" <davidvlu@gmail.com>
Maintainer-email: "David V. Lu!!" <davidvlu@gmail.com>
License-File: LICENSE
Classifier: License :: OSI Approved :: BSD License
Classifier: Operating System :: OS Independent
Classifier: Programming Language :: Python :: 3
Classifier: Topic :: Database
Requires-Python: >=3.8
Requires-Dist: pyyaml
Requires-Dist: tabulate
Provides-Extra: test
Requires-Dist: pytest-cov>=2; extra == 'test'
Requires-Dist: pytest>=4; extra == 'test'
